Workbook

Sheet StockAnalysis_JSG_All_Enriched_
A1: Symbol | B1: Type | C1: Name | D1: Dividend Yield | E1: Growth Score | F1: Optionable | G1: Weekly Verdict | H1: Direction | I1: Confidence % | J1: SELL PUT Suitability | K1: SELL CALL Suitability | L1: Premium ROI
A2: WDC | B2: EQ | C2: Western Digital Corporation | D2: 0.0011 | E2: 83.7 | F2: Yes | G2: STRONG_BULLISH | H2: BULLISH | I2: 77.97 | J2: High | K2: Covered call only if already held | L2: 13.28% (SELL PUT, exp 20260821)
A3: AMAT | B3: EQ | C3: Applied Materials, Inc. | D3: 0.0042 | E3: 83.7 | F3: Yes | G3: STRONG_BULLISH | H3: BULLISH | I3: 83.51 | J3: High | K3: Covered call only if already held | L3: 10.79% (SELL PUT, exp 20260821)
A4: TER | B4: EQ | C4: Teradyne, Inc. | D4: 0.0014 | E4: 73.5 | F4: Yes | G4: STRONG_BULLISH | H4: BULLISH | I4: 76.03 | J4: High | K4: Covered call only if already held | L4: 13.01% (SELL PUT, exp 20260821)
A5: AMD | B5: EQ | C5: Advanced Micro Devices, Inc. | D5: - | E5: 92 | F5: Yes | G5: STRONG_BULLISH | H5: BULLISH | I5: 80.96 | J5: High | K5: Covered call only if already held | L5: 9.13% (SELL PUT, exp 20260821)
A6: COHR | B6: EQ | C6: Coherent Corp. | D6: - | E6: 99.7 | F6: Yes | G6: BULLISH | H6: MIXED | I6: 34.04 | J6: Medium | K6: Medium covered-call candidate | L6: 12.63% (SELL PUT, exp 20260821)
A7: HPE | B7: EQ | C7: Hewlett Packard Enterprise Company | D7: 0.0119 | E7: 82.4 | F7: Yes | G7: STRONG_BULLISH | H7: BULLISH | I7: 97.68 | J7: High | K7: Covered call only if already held | L7: 7.38% (SELL PUT, exp 20260821)
A8: VRT | B8: EQ | C8: Vertiv Holdings Co | D8: 0.001 | E8: 89.3 | F8: Yes | G8: STRONG_BULLISH | H8: BULLISH | I8: 73.11 | J8: High | K8: Covered call only if already held | L8: 8.18% (SELL PUT, exp 20260821)
A9: DELL | B9: EQ | C9: Dell Technologies Inc. | D9: 0.0062 | E9: 86 | F9: Yes | G9: STRONG_BULLISH | H9: BULLISH | I9: 55.12 | J9: High | K9: Covered call only if already held | L9: 8.95% (SELL PUT, exp 20260821)
A10: DDOG | B10: EQ | C10: Datadog, Inc. | D10: - | E10: 75.7 | F10: Yes | G10: BULLISH | H10: BULLISH | I10: 77.12 | J10: High | K10: Covered call only if already held | L10: 7.70% (SELL PUT, exp 20260821)
A11: INTC | B11: EQ | C11: Intel Corporation | D11: - | E11: 78.8 | F11: Yes | G11: STRONG_BULLISH | H11: MIXED | I11: 31.95 | J11: Medium | K11: Medium covered-call candidate | L11: 11.70% (SELL PUT, exp 20260821)
A12: LITE | B12: EQ | C12: Lumentum Holdings Inc. | D12: - | E12: 100 | F12: Yes | G12: STRONG_BULLISH | H12: BULLISH | I12: 94.25 | J12: Medium-High | K12: Covered call only if already held
A13: STT | B13: EQ | C13: State Street Corporation | D13: 0.02 | E13: 72.5 | F13: Yes | G13: STRONG_BULLISH | H13: BULLISH | I13: 100 | J13: Medium-High | K13: Covered call only if already held
A14: FTNT | B14: EQ | C14: Fortinet, Inc. | D14: - | E14: 74.7 | F14: Yes | G14: BULLISH | H14: BULLISH | I14: 63.35 | J14: High | K14: Covered call only if already held | L14: 7.72% (SELL PUT, exp 20260821)
A15: PSX | B15: EQ | C15: Phillips 66 | D15: 0.024 | E15: 66.6 | F15: Yes | G15: STRONG_BULLISH | H15: BULLISH | I15: 100 | J15: Medium-High | K15: Covered call only if already held
A16: CFG | B16: EQ | C16: Citizens Financial Group, Inc. | D16: 0.0257 | E16: 64 | F16: Yes | G16: STRONG_BULLISH | H16: BULLISH | I16: 97.65 | J16: Medium-High | K16: Covered call only if already held
A17: HST | B17: EQ | C17: Host Hotels & Resorts, Inc. | D17: 0.0378 | E17: 60.1 | F17: Yes | G17: STRONG_BULLISH | H17: BULLISH | I17: 100 | J17: Medium-High | K17: Covered call only if already held
A18: ANET | B18: EQ | C18: Arista Networks, Inc. | D18: - | E18: 82.8 | F18: Yes | G18: STRONG_BULLISH | H18: BULLISH | I18: 100 | J18: Medium-High | K18: Covered call only if already held
A19: VTRS | B19: EQ | C19: Viatris Inc. | D19: 0.0273 | E19: 57.9 | F19: Yes | G19: STRONG_BULLISH | H19: BULLISH | I19: 100 | J19: Medium-High | K19: Covered call only if already held
A20: CASY | B20: EQ | C20: Casey's General Stores, Inc. | D20: 0.003 | E20: 79.7 | F20: Yes | G20: STRONG_BULLISH | H20: BULLISH | I20: 100 | J20: Medium-High | K20: Covered call only if already held
A21: CAT | B21: EQ | C21: Caterpillar Inc. | D21: 0.008 | E21: 79.6 | F21: Yes | G21: STRONG_BULLISH | H21: BULLISH | I21: 99.9 | J21: Medium-High | K21: Covered call only if already held
A22: WAB | B22: EQ | C22: Westinghouse Air Brake Technologies Corporation | D22: 0.0043 | E22: 79 | F22: Yes | G22: STRONG_BULLISH | H22: BULLISH | I22: 100 | J22: Medium-High | K22: Covered call only if already held
A23: SPG | B23: EQ | C23: Simon Property Group, Inc. | D23: 0.0392 | E23: 55.3 | F23: Yes | G23: STRONG_BULLISH | H23: BULLISH | I23: 100 | J23: Medium-High | K23: Covered call only if already held
A24: HWM | B24: EQ | C24: Howmet Aerospace Inc. | D24: 0.002 | E24: 78 | F24: Yes | G24: STRONG_BULLISH | H24: BULLISH | I24: 100 | J24: Medium-High | K24: Covered call only if already held
A25: FITB | B25: EQ | C25: Fifth Third Bancorp | D25: 0.0283 | E25: 55 | F25: Yes | G25: STRONG_BULLISH | H25: BULLISH | I25: 100 | J25: Medium-High | K25: Covered call only if already held
A26: CVS | B26: EQ | C26: CVS Health Corporation | D26: 0.0255 | E26: 54.9 | F26: Yes | G26: STRONG_BULLISH | H26: BULLISH | I26: 100 | J26: Medium-High | K26: Covered call only if already held
A27: XOM | B27: EQ | C27: ExxonMobil Holdings Corporation | D27: 0.0265 | E27: 54.7 | F27: Yes | G27: STRONG_BULLISH | H27: BULLISH | I27: 100 | J27: Medium-High | K27: Covered call only if already held
A28: APA | B28: EQ | C28: APA Corporation | D28: 0.0268 | E28: 54.5 | F28: Yes | G28: STRONG_BULLISH | H28: BULLISH | I28: 100 | J28: Medium-High | K28: Covered call only if already held
A29: VTR | B29: EQ | C29: Ventas, Inc. | D29: 0.0222 | E29: 54.3 | F29: Yes | G29: STRONG_BULLISH | H29: BULLISH | I29: 100 | J29: Medium-High | K29: Covered call only if already held
A30: MPC | B30: EQ | C30: Marathon Petroleum Corporation | D30: 0.0126 | E30: 75.7 | F30: Yes | G30: STRONG_BULLISH | H30: BULLISH | I30: 100 | J30: Medium-High | K30: Covered call only if already held
... A34: ABBV | B34: EQ | C34: AbbVie Inc. | D34: 0.0276 | E34: 52.2 | F34: Yes | G34: STRONG_BULLISH | H34: BULLISH | I34: 100 | J34: Medium-High | K34: Covered call only if already held
A35: PANW | B35: EQ | C35: Palo Alto Networks, Inc. | D35: - | E35: 86.5 | F35: Yes | G35: STRONG_BULLISH | H35: BULLISH | I35: 83.91 | J35: Medium-High | K35: Covered call only if already held
A36: MRK | B36: EQ | C36: Merck & Co., Inc. | D36: 0.0261 | E36: 51.6 | F36: Yes | G36: STRONG_BULLISH | H36: BULLISH | I36: 100 | J36: Medium-High | K36: Covered call only if already held
A37: GS | B37: EQ | C37: The Goldman Sachs Group, Inc. | D37: 0.0196 | E37: 74.3 | F37: Yes | G37: STRONG_BULLISH | H37: BULLISH | I37: 100 | J37: Medium-High | K37: Covered call only if already held
A38: MTB | B38: EQ | C38: M&T Bank Corporation | D38: 0.0244 | E38: 51.2 | F38: Yes | G38: STRONG_BULLISH | H38: BULLISH | I38: 100 | J38: Medium-High | K38: Covered call only if already held
A39: PM | B39: EQ | C39: Philip Morris International Inc. | D39: 0.0308 | E39: 50.9 | F39: Yes | G39: STRONG_BULLISH | H39: BULLISH | I39: 100 | J39: Medium-High | K39: Covered call only if already held
A40: UAL | B40: EQ | C40: United Airlines Holdings, Inc. | D40: - | E40: 73.4 | F40: Yes | G40: STRONG_BULLISH | H40: BULLISH | I40: 100 | J40: Medium-High | K40: Covered call only if already held
A41: APH | B41: EQ | C41: Amphenol Corporation | D41: 0.0062 | E41: 83.6 | F41: Yes | G41: STRONG_BULLISH | H41: BULLISH | I41: 85.3 | J41: Medium-High | K41: Covered call only if already held
A42: JNJ | B42: EQ | C42: Johnson & Johnson | D42: 0.0209 | E42: 50.2 | F42: Yes | G42: STRONG_BULLISH | H42: BULLISH | I42: 100 | J42: Medium-High | K42: Covered call only if already held
A43: FANG | B43: EQ | C43: Diamondback Energy, Inc. | D43: 0.0217 | E43: 49.9 | F43: Yes | G43: STRONG_BULLISH | H43: BULLISH | I43: 100 | J43: Medium-High | K43: Covered call only if already held
A44: USB | B44: EQ | C44: U.S. Bancorp | D44: 0.033 | E44: 48.3 | F44: Yes | G44: STRONG_BULLISH | H44: BULLISH | I44: 100 | J44: Medium-High | K44: Covered call only if already held
A45: PCAR | B45: EQ | C45: PACCAR Inc | D45: 0.0211 | E45: 48.3 | F45: Yes | G45: STRONG_BULLISH | H45: BULLISH | I45: 100 | J45: Medium-High | K45: Covered call only if already held
A46: DAL | B46: EQ | C46: Delta Air Lines, Inc. | D46: 0.0098 | E46: 70.5 | F46: Yes | G46: STRONG_BULLISH | H46: BULLISH | I46: 100 | J46: Medium-High | K46: Covered call only if already held
A47: WRB | B47: EQ | C47: W. R. Berkley Corporation | D47: 0.0262 | E47: 47.2 | F47: Yes | G47: STRONG_BULLISH | H47: BULLISH | I47: 100 | J47: Medium-High | K47: Covered call only if already held
A48: NVDA | B48: EQ | C48: NVIDIA Corporation | D48: 0.005 | E48: 75.7 | F48: Yes | G48: STRONG_BULLISH | H48: BULLISH | I48: 91.65 | J48: Medium-High | K48: Covered call only if already held
A49: DVA | B49: EQ | C49: DaVita Inc. | D49: - | E49: 69.5 | F49: Yes | G49: STRONG_BULLISH | H49: BULLISH | I49: 100 | J49: Medium-High | K49: Covered call only if already held
A50: GM | B50: EQ | C50: General Motors Company | D50: 0.0081 | E50: 69.5 | F50: Yes | G50: STRONG_BULLISH | H50: BULLISH | I50: 100 | J50: Medium-High | K50: Covered call only if already held
A51: RF | B51: EQ | C51: Regions Financial Corporation | D51: 0.0388 | E51: 46.5 | F51: Yes | G51: STRONG_BULLISH | H51: BULLISH | I51: 100 | J51: Medium-High | K51: Covered call only if already held
A52: NTAP | B52: EQ | C52: NetApp, Inc. | D52: 0.0117 | E52: 68.6 | F52: Yes | G52: STRONG_BULLISH | H52: BULLISH | I52: 100 | J52: Medium-High | K52: Covered call only if already held
A53: WELL | B53: EQ | C53: Welltower Inc. | D53: 0.0145 | E53: 68.6 | F53: Yes | G53: STRONG_BULLISH | H53: BULLISH | I53: 100 | J53: Medium-High | K53: Covered call only if already held
A54: EIX | B54: EQ | C54: Edison International | D54: 0.0478 | E54: 44.7 | F54: Yes | G54: STRONG_BULLISH | H54: BULLISH | I54: 100 | J54: Medium-High | K54: Covered call only if already held
A55: MET | B55: EQ | C55: MetLife, Inc. | D55: 0.0247 | E55: 43.8 | F55: Yes | G55: STRONG_BULLISH | H55: BULLISH | I55: 100 | J55: Medium-High | K55: Covered call only if already held
A56: KMI | B56: EQ | C56: Kinder Morgan, Inc. | D56: 0.037 | E56: 47.7 | F56: Yes | G56: STRONG_BULLISH | H56: BULLISH | I56: 93.87 | J56: Medium-High | K56: Covered call only if already held
A57: AMGN | B57: EQ | C57: Amgen Inc. | D57: 0.0262 | E57: 43.3 | F57: Yes | G57: STRONG_BULLISH | H57: BULLISH | I57: 100 | J57: Medium-High | K57: Covered call only if already held
A58: TFC | B58: EQ | C58: Truist Financial Corporation | D58: 0.0401 | E58: 42.3 | F58: Yes | G58: STRONG_BULLISH | H58: BULLISH | I58: 100 | J58: Medium-High | K58: Covered call only if already held
A59: CSCO | B59: EQ | C59: Cisco Systems, Inc. | D59: 0.0145 | E59: 65.1 | F59: Yes | G59: STRONG_BULLISH | H59: BULLISH | I59: 100 | J59: Medium-High | K59: Covered call only if already held
A60: EOG | B60: EQ | C60: EOG Resources, Inc. | D60: 0.0274 | E60: 41.6 | F60: Yes | G60: STRONG_BULLISH | H60: BULLISH | I60: 100 | J60: Medium-High | K60: Covered call only if already held
A61: RCL | B61: EQ | C61: Royal Caribbean Cruises Ltd. | D61: 0.0189 | E61: 64.1 | F61: Yes | G61: STRONG_BULLISH | H61: BULLISH | I61: 100 | J61: Medium-High | K61: Covered call only if already held
... A73: AIZ | B73: EQ | C73: Assurant, Inc. | D73: 0.0126 | E73: 59.9 | F73: Yes | G73: STRONG_BULLISH | H73: BULLISH | I73: 100 | J73: Medium-High | K73: Covered call only if already held
A74: INCY | B74: EQ | C74: Incyte Corporation | D74: - | E74: 59.9 | F74: Yes | G74: STRONG_BULLISH | H74: BULLISH | I74: 100 | J74: Medium-High | K74: Covered call only if already held
A75: REG | B75: EQ | C75: Regency Centers Corporation | D75: 0.0376 | E75: 36.8 | F75: Yes | G75: STRONG_BULLISH | H75: BULLISH | I75: 100 | J75: Medium-High | K75: Covered call only if already held
A76: DOC | B76: EQ | C76: Healthpeak Properties, Inc. | D76: 0.0559 | E76: 36.1 | F76: Yes | G76: STRONG_BULLISH | H76: BULLISH | I76: 100 | J76: Medium-High | K76: Covered call only if already held
A77: GEV | B77: EQ | C77: GE Vernova Inc. | D77: 0.002 | E77: 65.1 | F77: Yes | G77: STRONG_BULLISH | H77: MIXED | I77: 31.61 | J77: Medium | K77: Medium covered-call candidate | L77: 7.42% (SELL PUT, exp 20260821)
A78: LNT | B78: EQ | C78: Alliant Energy Corporation | D78: 0.0302 | E78: 35.6 | F78: Yes | G78: STRONG_BULLISH | H78: BULLISH | I78: 100 | J78: Medium-High | K78: Covered call only if already held
A79: DTE | B79: EQ | C79: DTE Energy Company | D79: 0.0329 | E79: 35.1 | F79: Yes | G79: STRONG_BULLISH | H79: BULLISH | I79: 100 | J79: Medium-High | K79: Covered call only if already held
A80: ALL | B80: EQ | C80: The Allstate Corporation | D80: 0.0164 | E80: 57.9 | F80: Yes | G80: STRONG_BULLISH | H80: BULLISH | I80: 100 | J80: Medium-High | K80: Covered call only if already held
A81: EXPE | B81: EQ | C81: Expedia Group, Inc. | D81: 0.0065 | E81: 69.5 | F81: Yes | G81: BULLISH | H81: BULLISH | I81: 83.48 | J81: Medium-High | K81: Covered call only if already held
A82: AVGO | B82: EQ | C82: Broadcom Inc. | D82: 0.0067 | E82: 74.1 | F82: Yes | G82: STRONG_BULLISH | H82: BULLISH | I82: 75.3 | J82: Medium-High | K82: Covered call only if already held
A83: JPM | B83: EQ | C83: JPMorgan Chase & Co. | D83: 0.0171 | E83: 56.1 | F83: Yes | G83: STRONG_BULLISH | H83: BULLISH | I83: 100 | J83: Medium-High | K83: Covered call only if already held
A84: SNA | B84: EQ | C84: Snap-on Incorporated | D84: 0.0238 | E84: 48.2 | F84: Yes | G84: STRONG_BULLISH | H84: BULLISH | I84: 78.36 | J84: Medium-High | K84: Covered call only if already held
A85: BBY | B85: EQ | C85: Best Buy Co., Inc. | D85: 0.0445 | E85: 32.7 | F85: Yes | G85: STRONG_BULLISH | H85: BULLISH | I85: 100 | J85: Medium-High | K85: Covered call only if already held
A86: EG | B86: EQ | C86: Everest Group, Ltd. | D86: 0.0214 | E86: 32.6 | F86: Yes | G86: STRONG_BULLISH | H86: BULLISH | I86: 100 | J86: Medium-High | K86: Covered call only if already held
A87: GWW | B87: EQ | C87: W.W. Grainger, Inc. | D87: 0.0072 | E87: 55.2 | F87: Yes | G87: STRONG_BULLISH | H87: BULLISH | I87: 100 | J87: Medium-High | K87: Covered call only if already held
A88: AEE | B88: EQ | C88: Ameren Corporation | D88: 0.0274 | E88: 35.4 | F88: Yes | G88: STRONG_BULLISH | H88: BULLISH | I88: 95.63 | J88: Medium-High | K88: Covered call only if already held
A89: SO | B89: EQ | C89: The Southern Company | D89: 0.0322 | E89: 32 | F89: Yes | G89: STRONG_BULLISH | H89: BULLISH | I89: 100 | J89: Medium-High | K89: Covered call only if already held
... A99: D | B99: EQ | C99: Dominion Energy, Inc. | D99: 0.0386 | E99: 37.7 | F99: Yes | G99: STRONG_BULLISH | H99: BULLISH | I99: 87.53 | J99: Medium-High | K99: Covered call only if already held
A100: HOOD | B100: EQ | C100: Robinhood Markets, Inc. | D100: - | E100: 55.7 | F100: Yes | G100: STRONG_BULLISH | H100: MIXED | I100: 33.32 | J100: Medium | K100: Medium covered-call candidate | L100: 7.62% (SELL PUT, exp 20260821)
A101: ADM | B101: EQ | C101: Archer-Daniels-Midland Company | D101: 0.0262 | E101: 36.8 | F101: Yes | G101: STRONG_BULLISH | H101: BULLISH | I101: 88.18 | J101: Medium-High | K101: Covered call only if already held
A102: TPL | B102: EQ | C102: Texas Pacific Land Corporation | D102: 0.006 | E102: 59.4 | F102: Yes | G102: STRONG_BULLISH | H102: BULLISH | I102: 87.78 | J102: Medium-High | K102: Covered call only if already held
A103: EXR | B103: EQ | C103: Extra Space Storage Inc. | D103: 0.0438 | E103: 27.8 | F103: Yes | G103: STRONG_BULLISH | H103: BULLISH | I103: 100 | J103: Medium-High | K103: Covered call only if already held
A104: AFL | B104: EQ | C104: Aflac Incorporated | D104: 0.0191 | E104: 50.1 | F104: Yes | G104: STRONG_BULLISH | H104: BULLISH | I104: 100 | J104: Medium-High | K104: Covered call only if already held
A105: UPS | B105: EQ | C105: United Parcel Service, Inc. | D105: 0.0629 | E105: 27.5 | F105: Yes | G105: STRONG_BULLISH | H105: BULLISH | I105: 99.52 | J105: Medium-High | K105: Covered call only if already held
A106: DGX | B106: EQ | C106: Quest Diagnostics Incorporated | D106: 0.0148 | E106: 49.3 | F106: Yes | G106: STRONG_BULLISH | H106: BULLISH | I106: 100 | J106: Medium-High | K106: Covered call only if already held
A107: AAPL | B107: EQ | C107: Apple Inc. | D107: 0.0035 | E107: 49.2 | F107: Yes | G107: STRONG_BULLISH | H107: BULLISH | I107: 100 | J107: Medium-High | K107: Covered call only if already held
A108: JBHT | B108: EQ | C108: J.B. Hunt Transport Services, Inc. | D108: 0.0066 | E108: 48.9 | F108: Yes | G108: STRONG_BULLISH | H108: BULLISH | I108: 100 | J108: Medium-High | K108: Covered call only if already held
A109: BXP | B109: EQ | C109: BXP, Inc. | D109: 0.0399 | E109: 25.8 | F109: Yes | G109: STRONG_BULLISH | H109: BULLISH | I109: 100 | J109: Medium-High | K109: Covered call only if already held
A110: APP | B110: EQ | C110: AppLovin Corporation | D110: - | E110: 78.7 | F110: Yes | G110: CAUTION | H110: BEARISH | I110: 44.34 | J110: Avoid/Wait | K110: Medium covered-call candidate | L110: 9.17% (SELL PUT, exp 20260821)
A111: SJM | B111: EQ | C111: The J. M. Smucker Company | D111: 0.0376 | E111: 25.5 | F111: Yes | G111: STRONG_BULLISH | H111: BULLISH | I111: 100 | J111: Medium-High | K111: Covered call only if already held
A112: ETN | B112: EQ | C112: Eaton Corporation plc | D112: 0.0106 | E112: 48.1 | F112: Yes | G112: STRONG_BULLISH | H112: BULLISH | I112: 100 | J112: Medium-High | K112: Covered call only if already held
A113: PCG | B113: EQ | C113: PG&E Corporation | D113: 0.0115 | E113: 48.1 | F113: Yes | G113: STRONG_BULLISH | H113: BULLISH | I113: 100 | J113: Medium-High | K113: Covered call only if already held
A114: FCX | B114: EQ | C114: Freeport-McMoRan Inc. | D114: 0.0096 | E114: 55.7 | F114: Yes | G114: STRONG_BULLISH | H114: BULLISH | I114: 89.28 | J114: Medium-High | K114: Covered call only if already held
A115: CB | B115: EQ | C115: Chubb Limited | D115: 0.0116 | E115: 47.9 | F115: Yes | G115: STRONG_BULLISH | H115: BULLISH | I115: 100 | J115: Medium-High | K115: Covered call only if already held
A116: ADP | B116: EQ | C116: Automatic Data Processing, Inc. | D116: 0.0255 | E116: 25 | F116: Yes | G116: STRONG_BULLISH | H116: BULLISH | I116: 100 | J116: Medium-High | K116: Covered call only if already held
A117: PFG | B117: EQ | C117: Principal Financial Group, Inc. | D117: 0.0295 | E117: 51.1 | F117: Yes | G117: BULLISH | H117: BULLISH | I117: 62.71 | J117: Medium-High | K117: Covered call only if already held
A118: HPQ | B118: EQ | C118: HP Inc. | D118: 0.044 | E118: 24.3 | F118: Yes | G118: STRONG_BULLISH | H118: BULLISH | I118: 100 | J118: Medium-High | K118: Covered call only if already held
A119: MDLZ | B119: EQ | C119: Mondelez International, Inc. | D119: 0.0321 | E119: 24.3 | F119: Yes | G119: STRONG_BULLISH | H119: BULLISH | I119: 100 | J119: Medium-High | K119: Covered call only if already held
A120: CPT | B120: EQ | C120: Camden Property Trust | D120: 0.0383 | E120: 24.1 | F120: Yes | G120: STRONG_BULLISH | H120: BULLISH | I120: 100 | J120: Medium-High | K120: Covered call only if already held
A121: AME | B121: EQ | C121: AMETEK, Inc. | D121: 0.0056 | E121: 46.9 | F121: Yes | G121: STRONG_BULLISH | H121: BULLISH | I121: 100 | J121: Medium-High | K121: Covered call only if already held
A122: CSX | B122: EQ | C122: CSX Corporation | D122: 0.0111 | E122: 46.7 | F122: Yes | G122: STRONG_BULLISH | H122: BULLISH | I122: 100 | J122: Medium-High | K122: Covered call only if already held
... A124: GD | B124: EQ | C124: General Dynamics Corporation | D124: 0.0166 | E124: 46.2 | F124: Yes | G124: STRONG_BULLISH | H124: BULLISH | I124: 100 | J124: Medium-High | K124: Covered call only if already held
...

Sheet newlist
A1: AssetClass | B1: Symbol | C1: InOld
A2: EQ | B2: A | C2: =IF(ISERROR(_xlfn.XMATCH(B2,oldlist!B:B,0)),"not found","found") -> found
A3: EQ | B3: AAPL | C3: =IF(ISERROR(_xlfn.XMATCH(B3,oldlist!B:B,0)),"not found","found") -> found
A4: EQ | B4: ABBV | C4: =IF(ISERROR(_xlfn.XMATCH(B4,oldlist!B:B,0)),"not found","found") -> found
A5: EQ | B5: ABNB | C5: =IF(ISERROR(_xlfn.XMATCH(B5,oldlist!B:B,0)),"not found","found") -> found
A6: EQ | B6: ABT | C6: =IF(ISERROR(_xlfn.XMATCH(B6,oldlist!B:B,0)),"not found","found") -> found
A7: EQ | B7: ACGL | C7: =IF(ISERROR(_xlfn.XMATCH(B7,oldlist!B:B,0)),"not found","found") -> found
A8: EQ | B8: ACN | C8: =IF(ISERROR(_xlfn.XMATCH(B8,oldlist!B:B,0)),"not found","found") -> found
A9: EQ | B9: ADBE | C9: =IF(ISERROR(_xlfn.XMATCH(B9,oldlist!B:B,0)),"not found","found") -> found
A10: EQ | B10: ADI | C10: =IF(ISERROR(_xlfn.XMATCH(B10,oldlist!B:B,0)),"not found","found") -> found
A11: EQ | B11: ADM | C11: =IF(ISERROR(_xlfn.XMATCH(B11,oldlist!B:B,0)),"not found","found") -> found
A12: EQ | B12: ADP | C12: =IF(ISERROR(_xlfn.XMATCH(B12,oldlist!B:B,0)),"not found","found") -> found
A13: EQ | B13: ADSK | C13: =IF(ISERROR(_xlfn.XMATCH(B13,oldlist!B:B,0)),"not found","found") -> found
... A1370: ETF | B1370: YLDE | C1370: =IF(ISERROR(_xlfn.XMATCH(B1370,oldlist!B:B,0)),"not found","found") -> not found

Sheet oldlist
A1: AssetClass | B1: Symbol | C1: InNew
A2: EQ | B2: A | C2: =IF(ISERROR(_xlfn.XMATCH(B2,newlist!B:B,0)),"not found","found") -> found
A3: EQ | B3: AAPL | C3: =IF(ISERROR(_xlfn.XMATCH(B3,newlist!B:B,0)),"not found","found") -> found
A4: EQ | B4: ABBV | C4: =IF(ISERROR(_xlfn.XMATCH(B4,newlist!B:B,0)),"not found","found") -> found
A5: EQ | B5: ABNB | C5: =IF(ISERROR(_xlfn.XMATCH(B5,newlist!B:B,0)),"not found","found") -> found
A6: EQ | B6: ABT | C6: =IF(ISERROR(_xlfn.XMATCH(B6,newlist!B:B,0)),"not found","found") -> found
A7: EQ | B7: ACGL | C7: =IF(ISERROR(_xlfn.XMATCH(B7,newlist!B:B,0)),"not found","found") -> found
A8: EQ | B8: ADBE | C8: =IF(ISERROR(_xlfn.XMATCH(B8,newlist!B:B,0)),"not found","found") -> found
A9: EQ | B9: ADI | C9: =IF(ISERROR(_xlfn.XMATCH(B9,newlist!B:B,0)),"not found","found") -> found
A10: EQ | B10: ADM | C10: =IF(ISERROR(_xlfn.XMATCH(B10,newlist!B:B,0)),"not found","found") -> found
A11: EQ | B11: ADP | C11: =IF(ISERROR(_xlfn.XMATCH(B11,newlist!B:B,0)),"not found","found") -> found
A12: EQ | B12: AEE | C12: =IF(ISERROR(_xlfn.XMATCH(B12,newlist!B:B,0)),"not found","found") -> found
A13: EQ | B13: AEP | C13: =IF(ISERROR(_xlfn.XMATCH(B13,newlist!B:B,0)),"not found","found") -> found
... A1213: ETF | B1213: XOEF | C1213: =IF(ISERROR(_xlfn.XMATCH(B1213,newlist!B:B,0)),"not found","found") -> found

Sheet summary
A1: InOld | D1: InNew
A2: found | B2: =COUNTIF(newlist!C:C,A2) -> 1183 | D2: found | E2: =COUNTIF(oldlist!C:C,A2) -> 1183
A3: not found | B3: =COUNTIF(newlist!C:C,A3) -> 186 | D3: not found | E3: =COUNTIF(oldlist!C:C,A3) -> 29
